{
    "products": [
        {
            "StockCode": "22141",
            "Description": "CHRISTMAS CRAFT TREE TOP ANGEL",
            "Quantity": 1,
            "UnitPrice": 2.1
        },
        {
            "StockCode": "35591T",
            "Description": "TURQUOISE CHRISTMAS TREE ",
            "Quantity": 2,
            "UnitPrice": 1.25
        },
        {
            "StockCode": "22594",
            "Description": "CHRISTMAS GINGHAM TREE",
            "Quantity": 5,
            "UnitPrice": 0.85
        },
        {
            "StockCode": "21816",
            "Description": "CHRISTMAS TREE T-LIGHT HOLDER",
            "Quantity": 2,
            "UnitPrice": 1.45
        },
        {
            "StockCode": "22603",
            "Description": "CHRISTMAS RETROSPOT TREE WOOD",
            "Quantity": 2,
            "UnitPrice": 0.85
        }
    ]
}